ms_salesforce_api/__init__.py
ms_salesforce_api/salesforce/Auth.py
ms_salesforce_api/salesforce/JWTGenerator.py
ms_salesforce_api/salesforce/SalesforceQueryExecutor.py
ms_salesforce_api/salesforce/__init__.py
ms_salesforce_api/salesforce/__tests__/__init__.py
ms_salesforce_api/salesforce/__tests__/test_Auth.py
ms_salesforce_api/salesforce/__tests__/test_JWTGenerator.py
ms_salesforce_api/salesforce/__tests__/test_SalesforceRequester.py
ms_salesforce_api/salesforce/api/__init__.py
ms_salesforce_api/salesforce/api/account/__init__.py
ms_salesforce_api/salesforce/api/account/constants.py
ms_salesforce_api/salesforce/api/account/dto/AccountDTO.py
ms_salesforce_api/salesforce/api/account/dto/__init__.py
ms_salesforce_api/salesforce/api/account/export_data/Bigquery.py
ms_salesforce_api/salesforce/api/account/export_data/__init__.py
ms_salesforce_api/salesforce/api/addtech_onboarding/__init__.py
ms_salesforce_api/salesforce/api/addtech_onboarding/constants.py
ms_salesforce_api/salesforce/api/addtech_onboarding/dto/AddTechOnboarding.py
ms_salesforce_api/salesforce/api/addtech_onboarding/dto/__init__.py
ms_salesforce_api/salesforce/api/addtech_onboarding/export_data/Bigquery.py
ms_salesforce_api/salesforce/api/addtech_onboarding/export_data/__init__.py
ms_salesforce_api/salesforce/api/contact/__init__.py
ms_salesforce_api/salesforce/api/contact/constants.py
ms_salesforce_api/salesforce/api/contact/dto/ContactDTO.py
ms_salesforce_api/salesforce/api/contact/dto/__init__.py
ms_salesforce_api/salesforce/api/contact/export_data/Bigquery.py
ms_salesforce_api/salesforce/api/contact/export_data/__init__.py
ms_salesforce_api/salesforce/api/lead/__init__.py
ms_salesforce_api/salesforce/api/lead/constants.py
ms_salesforce_api/salesforce/api/lead/dto/LeadDTO.py
ms_salesforce_api/salesforce/api/lead/dto/__init__.py
ms_salesforce_api/salesforce/api/lead/export_data/Bigquery.py
ms_salesforce_api/salesforce/api/lead/export_data/__init__.py
ms_salesforce_api-3.5.0.dist-info/METADATA
ms_salesforce_api-3.5.0.dist-info/WHEEL
ms_salesforce_api-3.5.0.dist-info/licenses/LICENSE
ms_salesforce_api-3.5.0.dist-info/RECORD
