Metadata-Version: 2.4
Name: ms-salesforce-api
Version: 3.5.0
Summary: Python library used to extract data from Salesforce API and migrate it to Bigquery and Postgres.
License-File: LICENSE
Author: Making Science
Requires-Python: >=3.8.1,<4.0.0
Classifier: Programming Language :: Python :: 3
Classifier: Programming Language :: Python :: 3.9
Classifier: Programming Language :: Python :: 3.10
Classifier: Programming Language :: Python :: 3.11
Classifier: Programming Language :: Python :: 3.12
Classifier: Programming Language :: Python :: 3.13
Classifier: Programming Language :: Python :: 3.14
Requires-Dist: flake8 (>=6.0.0,<7.0.0)
Requires-Dist: gc-google-services-api (==2.4.0)
Requires-Dist: isort (>=5.12.0,<6.0.0)
Requires-Dist: pre-commit (>=3.1.1,<4.0.0)
Requires-Dist: psycopg2-binary (>=2.9.6,<3.0.0)
Requires-Dist: pyjwt[crypto] (>=2.6.0,<3.0.0)
Requires-Dist: requests (>=2.28.2,<3.0.0)
